pyntone/__init__.py
pyntone/kintone_request_config_builder.py
pyntone/kintone_rest_api_client.py
pyntone/url.py
pyntone/client/__init__.py
pyntone/client/app_client.py
pyntone/client/bulk_request_client.py
pyntone/client/file_client.py
pyntone/client/record_client.py
pyntone/client/types/__init__.py
pyntone/client/types/app/__init__.py
pyntone/client/types/app/customize.py
pyntone/http/__init__.py
pyntone/http/http_client.py
pyntone/types/__init__.py
pyntone/types/auth.py
pyntone/types/record.py
pyntone-0.3.1.dist-info/METADATA
pyntone-0.3.1.dist-info/WHEEL
pyntone-0.3.1.dist-info/licenses/LICENSE
pyntone-0.3.1.dist-info/RECORD
